racepretextproc/__init__.py
racepretextproc/lemetstemtoken/__init__.py
racepretextproc/lemetstemtoken/lemetstemtoken.py
racepretextproc/noise_remove/__init__.py
racepretextproc/noise_remove/noise_remove.py
racepretextproc/normalization/__init__.py
racepretextproc/normalization/normalization.py
racepretextproc/visualization/__init__.py
racepretextproc/visualization/visualize.py
racepretextproc-0.0.5.dist-info/LICENSE
racepretextproc-0.0.5.dist-info/METADATA
racepretextproc-0.0.5.dist-info/WHEEL
racepretextproc-0.0.5.dist-info/top_level.txt
racepretextproc-0.0.5.dist-info/RECORD
